mcp_image_search/__init__.py
mcp_image_search/__main__.py
mcp_image_search/server.py
mcp_image_search/pyarmor_runtime_000000/__init__.py
mcp_image_search/pyarmor_runtime_000000/darwin_universal/pyarmor_runtime.so
iflow_mcp_image_search-0.1.3.dist-info/METADATA
iflow_mcp_image_search-0.1.3.dist-info/WHEEL
iflow_mcp_image_search-0.1.3.dist-info/entry_points.txt
iflow_mcp_image_search-0.1.3.dist-info/licenses/LICENSE
iflow_mcp_image_search-0.1.3.dist-info/RECORD
