Metadata-Version: 2.4
Name: iflow-mcp_image-search
Version: 0.1.3
Summary: A Model Context Protocol server providing image search and download capabilities
Author: MCP Image Search Team
License: MIT
License-File: LICENSE
Keywords: automation,download,image-search,llm,mcp
Classifier: Development Status :: 4 - Beta
Classifier: Intended Audience :: Developers
Classifier: License :: OSI Approved :: MIT License
Classifier: Programming Language :: Python :: 3
Classifier: Programming Language :: Python :: 3.10
Classifier: Programming Language :: Python :: 3.11
Classifier: Programming Language :: Python :: 3.12
Requires-Python: ==3.12.7
Requires-Dist: mcp>=1.1.3
Requires-Dist: pydantic>=2.0.0
Requires-Dist: requests>=2.25.0
